Metadata-Version: 1.0
Name: sancopack
Version: 0.0.2
Summary: collect packages
Home-page: https://www.winrobot360.com
Author: sanco
Author-email: sanco1987@gmail.com
License: UNKNOWN
Platform: UNKNOWN
